alibabacloud_ossmfd20231017/__init__.py
alibabacloud_ossmfd20231017/client.py
alibabacloud_ossmfd20231017/models/__init__.py
alibabacloud_ossmfd20231017/models/_check_mfd_service_open_response.py
alibabacloud_ossmfd20231017/models/_check_mfd_service_open_response_body.py
alibabacloud_ossmfd20231017/models/_create_oss_bucket_scan_task_request.py
alibabacloud_ossmfd20231017/models/_create_oss_bucket_scan_task_response.py
alibabacloud_ossmfd20231017/models/_create_oss_bucket_scan_task_response_body.py
alibabacloud_ossmfd20231017/models/_create_oss_scan_config_request.py
alibabacloud_ossmfd20231017/models/_create_oss_scan_config_response.py
alibabacloud_ossmfd20231017/models/_create_oss_scan_config_response_body.py
alibabacloud_ossmfd20231017/models/_describe_export_info_request.py
alibabacloud_ossmfd20231017/models/_describe_export_info_response.py
alibabacloud_ossmfd20231017/models/_describe_export_info_response_body.py
alibabacloud_ossmfd20231017/models/_describe_service_linked_role_status_request.py
alibabacloud_ossmfd20231017/models/_describe_service_linked_role_status_response.py
alibabacloud_ossmfd20231017/models/_describe_service_linked_role_status_response_body.py
alibabacloud_ossmfd20231017/models/_export_record_request.py
alibabacloud_ossmfd20231017/models/_export_record_response.py
alibabacloud_ossmfd20231017/models/_export_record_response_body.py
alibabacloud_ossmfd20231017/models/_get_file_detect_report_request.py
alibabacloud_ossmfd20231017/models/_get_file_detect_report_response.py
alibabacloud_ossmfd20231017/models/_get_file_detect_report_response_body.py
alibabacloud_ossmfd20231017/models/_get_oss_bucket_scan_statistic_request.py
alibabacloud_ossmfd20231017/models/_get_oss_bucket_scan_statistic_response.py
alibabacloud_ossmfd20231017/models/_get_oss_bucket_scan_statistic_response_body.py
alibabacloud_ossmfd20231017/models/_get_oss_scan_config_request.py
alibabacloud_ossmfd20231017/models/_get_oss_scan_config_response.py
alibabacloud_ossmfd20231017-1.0.1.dist-info/LICENSE
alibabacloud_ossmfd20231017-1.0.1.dist-info/METADATA
alibabacloud_ossmfd20231017-1.0.1.dist-info/WHEEL
alibabacloud_ossmfd20231017-1.0.1.dist-info/top_level.txt
alibabacloud_ossmfd20231017-1.0.1.dist-info/RECORD
